czds/__init__.py
czds/__main__.py
czds/client.py
czds/utils.py
czds_api-1.3.8.dist-info/licenses/LICENSE
czds_api-1.3.8.dist-info/METADATA
czds_api-1.3.8.dist-info/WHEEL
czds_api-1.3.8.dist-info/entry_points.txt
czds_api-1.3.8.dist-info/top_level.txt
czds_api-1.3.8.dist-info/RECORD
