Metadata-Version: 2.4
Name: czds-api
Version: 1.3.8
Summary: ICANN API for the Centralized Zones Data Service
Home-page: https://github.com/acidvegas/czds
Author: acidvegas
Author-email: acid.vegas@acid.vegas
Project-URL: Bug Tracker, https://github.com/acidvegas/czds/issues
Project-URL: Documentation, https://github.com/acidvegas/czds#readme
Project-URL: Source Code, https://github.com/acidvegas/czds
Classifier: Development Status :: 5 - Production/Stable
Classifier: Intended Audience :: Developers
Classifier: License :: OSI Approved :: ISC License (ISCL)
Classifier: Operating System :: OS Independent
Classifier: Programming Language :: Python :: 3
Classifier: Programming Language :: Python :: 3.6
Classifier: Programming Language :: Python :: 3.7
Classifier: Programming Language :: Python :: 3.8
Classifier: Programming Language :: Python :: 3.9
Classifier: Programming Language :: Python :: 3.10
Classifier: Programming Language :: Python :: 3.11
Classifier: Topic :: Internet
Classifier: Topic :: Security
Classifier: Topic :: Software Development :: Libraries :: Python Modules
Requires-Python: >=3.6
License-File: LICENSE
Requires-Dist: aiohttp>=3.8.0
Requires-Dist: aiofiles>=23.2.1
Dynamic: author
Dynamic: author-email
Dynamic: classifier
Dynamic: description
Dynamic: description-content-type
Dynamic: home-page
Dynamic: license-file
Dynamic: project-url
Dynamic: requires-dist
Dynamic: requires-python
Dynamic: summary
